mkdocs_llmstxt-0.4.0.dist-info/METADATA
mkdocs_llmstxt-0.4.0.dist-info/WHEEL
mkdocs_llmstxt-0.4.0.dist-info/entry_points.txt
mkdocs_llmstxt-0.4.0.dist-info/licenses/LICENSE
mkdocs_llmstxt/__init__.py
mkdocs_llmstxt/_internal/__init__.py
mkdocs_llmstxt/_internal/config.py
mkdocs_llmstxt/_internal/debug.py
mkdocs_llmstxt/_internal/logger.py
mkdocs_llmstxt/_internal/plugin.py
mkdocs_llmstxt/_internal/preprocess.py
mkdocs_llmstxt/py.typed
mkdocs_llmstxt-0.4.0.dist-info/RECORD
