Metadata-Version: 2.4
Name: mkdocs-llmstxt
Version: 0.4.0
Summary: MkDocs plugin to generate an /llms.txt file.
Author-Email: =?utf-8?q?Timoth=C3=A9e_Mazzucotelli?= <dev@pawamoy.fr>
License-Expression: ISC
License-File: LICENSE
Classifier: Development Status :: 4 - Beta
Classifier: Intended Audience :: Developers
Classifier: Programming Language :: Python
Classifier: Programming Language :: Python :: 3
Classifier: Programming Language :: Python :: 3 :: Only
Classifier: Programming Language :: Python :: 3.9
Classifier: Programming Language :: Python :: 3.10
Classifier: Programming Language :: Python :: 3.11
Classifier: Programming Language :: Python :: 3.12
Classifier: Programming Language :: Python :: 3.13
Classifier: Programming Language :: Python :: 3.14
Classifier: Topic :: Documentation
Classifier: Topic :: Software Development
Classifier: Topic :: Utilities
Classifier: Typing :: Typed
Project-URL: Homepage, https://pawamoy.github.io/mkdocs-llmstxt
Project-URL: Documentation, https://pawamoy.github.io/mkdocs-llmstxt
Project-URL: Changelog, https://pawamoy.github.io/mkdocs-llmstxt/changelog
Project-URL: Repository, https://github.com/pawamoy/mkdocs-llmstxt
Project-URL: Issues, https://github.com/pawamoy/mkdocs-llmstxt/issues
Project-URL: Discussions, https://github.com/pawamoy/mkdocs-llmstxt/discussions
Project-URL: Gitter, https://gitter.im/mkdocs-llmstxt/community
Project-URL: Funding, https://github.com/sponsors/pawamoy
Requires-Python: >=3.9
Requires-Dist: beautifulsoup4>=4.12
Requires-Dist: markdownify>=0.14
Requires-Dist: mdformat>=0.7.21
Requires-Dist: mdformat-tables>=1.0
